agent_state_bridge/__init__.py
agent_state_bridge/django.py
agent_state_bridge/fastapi.py
agent_state_bridge/flask.py
agent_state_bridge/models.py
agent_state_bridge-0.2.0.dist-info/METADATA
agent_state_bridge-0.2.0.dist-info/WHEEL
agent_state_bridge-0.2.0.dist-info/top_level.txt
agent_state_bridge-0.2.0.dist-info/RECORD
