Metadata-Version: 2.4
Name: agent-state-bridge
Version: 0.2.0
Summary: Python backend utilities for sharing app state with AI agents. New: {messages, actions, context} model for RAG-ready architecture.
Author: Sergio Cantera
License: MIT
Project-URL: Homepage, https://github.com/SergioCantera/agent-state-bridge
Project-URL: Repository, https://github.com/SergioCantera/agent-state-bridge
Project-URL: Issues, https://github.com/SergioCantera/agent-state-bridge/issues
Keywords: agent,state,chat,ai,fastapi,flask,django
Classifier: Development Status :: 3 - Alpha
Classifier: Intended Audience :: Developers
Classifier: License :: OSI Approved :: MIT License
Classifier: Programming Language :: Python :: 3
Classifier: Programming Language :: Python :: 3.9
Classifier: Programming Language :: Python :: 3.10
Classifier: Programming Language :: Python :: 3.11
Classifier: Programming Language :: Python :: 3.12
Requires-Python: >=3.9
Requires-Dist: pydantic>=2.0.0
Provides-Extra: fastapi
Requires-Dist: fastapi>=0.100.0; extra == "fastapi"
Provides-Extra: flask
Requires-Dist: flask>=2.0.0; extra == "flask"
Provides-Extra: django
Requires-Dist: djangorestframework>=3.14.0; extra == "django"
Provides-Extra: all
Requires-Dist: fastapi>=0.100.0; extra == "all"
Requires-Dist: flask>=2.0.0; extra == "all"
Requires-Dist: djangorestframework>=3.14.0; extra == "all"
